sonos_websocket/__init__.py
sonos_websocket/__main__.py
sonos_websocket/const.py
sonos_websocket/exception.py
sonos_websocket/websocket.py
sonos_websocket-0.1.3.dist-info/METADATA
sonos_websocket-0.1.3.dist-info/WHEEL
sonos_websocket-0.1.3.dist-info/top_level.txt
sonos_websocket-0.1.3.dist-info/RECORD
