Metadata-Version: 2.1
Name: sonos-websocket
Version: 0.1.3
Summary: An asynchronous Python library to communicate with Sonos devices over websockets.
Author-email: Jason Lawrence <jjlawren@users.noreply.github.com>
License: MIT License
Project-URL: Homepage, https://github.com/jjlawren/sonos-websocket
Classifier: Development Status :: 4 - Beta
Classifier: Intended Audience :: Developers
Classifier: License :: OSI Approved :: MIT License
Classifier: Operating System :: OS Independent
Classifier: Programming Language :: Python :: 3
Classifier: Topic :: Home Automation
Classifier: Topic :: Multimedia :: Sound/Audio
Classifier: Topic :: Multimedia :: Sound/Audio :: Players
Classifier: Topic :: Software Development :: Libraries :: Python Modules
Requires-Python: >=3.10
Requires-Dist: aiohttp
Requires-Dist: async_timeout; python_version < "3.11"
